poolmanager/__init__.py
poolmanager-0.2.1.dist-info/METADATA
poolmanager-0.2.1.dist-info/WHEEL
poolmanager-0.2.1.dist-info/top_level.txt
poolmanager-0.2.1.dist-info/RECORD
